djangorestframework_plist-0.3.0.dist-info/DESCRIPTION.rst
djangorestframework_plist-0.3.0.dist-info/METADATA
djangorestframework_plist-0.3.0.dist-info/RECORD
djangorestframework_plist-0.3.0.dist-info/WHEEL
djangorestframework_plist-0.3.0.dist-info/metadata.json
djangorestframework_plist-0.3.0.dist-info/top_level.txt
rest_framework_plist/__init__.py
rest_framework_plist/models.py
rest_framework_plist/parsers.py
rest_framework_plist/plist.py
rest_framework_plist/renderers.py
rest_framework_plist/tests.py
test_project/__init__.py
test_project/settings.py
test_project/urls.py
test_project/wsgi.py
